<?xml version="1.0" encoding="UTF-8"?>
<metadata xml:lang="es"><Esri><CreaDate>20231006</CreaDate><CreaTime>18111700</CreaTime><ArcGISFormat>1.0</ArcGISFormat><SyncOnce>TRUE</SyncOnce><DataProperties><lineage><Process ToolSource="c:\program files (x86)\arcgis\desktop10.5\ArcToolbox\Toolboxes\Data Management Tools.tbx\CalculateField" Date="20230124" Time="170611">CalculateField "Densidad residencial por manzana" ANO 44562 VB #</Process><Process ToolSource="c:\program files (x86)\arcgis\desktop10.5\ArcToolbox\Toolboxes\Data Management Tools.tbx\ConvertTimeField" Date="20230130" Time="170813">ConvertTimeField D:\Contenedor_old\lgalvis\Documents\lgalvis\Datos\OTC_IDECA\otc.gdb\Densidad_Resid_M ANO 'Not Used' ANO_Converted TEXT yyyy;22538;;</Process><Process ToolSource="c:\program files (x86)\arcgis\desktop10.5\ArcToolbox\Toolboxes\Data Management Tools.tbx\ConvertTimeField" Date="20230130" Time="171456">ConvertTimeField D:\Contenedor_old\lgalvis\Documents\lgalvis\Datos\OTC_IDECA\otc.gdb\Densidad_Resid_M ANO_Converted yyyy;22538;; ANO_Converted_Converted DATE 'Not Used'</Process><Process ToolSource="c:\program files (x86)\arcgis\desktop10.5\ArcToolbox\Toolboxes\Data Management Tools.tbx\Append" Date="20230613" Time="122806">Append D:\Contenedor\Users\lgalvis\Documents\ArcGIS\Default.gdb\residencial2021 D:\Contenedor_old\lgalvis\Documents\lgalvis\Datos\OTC_IDECA\2023\OTC2023.gdb\Densidad_Resid_M NO_TEST "MANCODIGO "Identificador único de la manzana" true true false 9 Text 0 0 ,First,#,D:\Contenedor\Users\lgalvis\Documents\ArcGIS\Default.gdb\residencial2021,MANCODIGO,-1,-1;AREA_RESIDENCIAL_CONSTRUIDA "Área residencial construida" true true false 8 Double 0 0 ,First,#,D:\Contenedor\Users\lgalvis\Documents\ArcGIS\Default.gdb\residencial2021,AREA_CONST,-1,-1;ANO "Año" true true false 8 Date 0 0 ,First,#;SHAPE_Length "SHAPE_Length" false true true 8 Double 0 0 ,First,#,D:\Contenedor\Users\lgalvis\Documents\ArcGIS\Default.gdb\residencial2021,Shape_Length,-1,-1;SHAPE_Area "SHAPE_Area" false true true 8 Double 0 0 ,First,#,D:\Contenedor\Users\lgalvis\Documents\ArcGIS\Default.gdb\residencial2021,Shape_Area,-1,-1" #</Process><Process ToolSource="c:\program files (x86)\arcgis\desktop10.5\ArcToolbox\Toolboxes\Data Management Tools.tbx\CalculateField" Date="20230613" Time="123456">CalculateField Densidad_Resid_M ANO 44197 VB #</Process><Process ToolSource="c:\program files (x86)\arcgis\desktop10.6\ArcToolbox\Toolboxes\Data Management Tools.tbx\Copy" Date="20230614" Time="181857">Copy D:\Contenedor\Users\mbernate\Desktop\20230614_OrdenamientoTerritorial.gdb\BogotaEvoluciona\Area_Constr_Resid_M D:\Contenedor\Users\mbernate\AppData\Local\ESRI\Desktop10.6\ArcCatalog\OCI\OCI@ORDENAMIENTOTERRITORIAL.sde\ORDENAMIENTOTERRITORIAL.BogotaEvoluciona\ORDENAMIENTOTERRITORIAL.Area_Constr_Resid_M FeatureClass</Process></lineage><itemProps><itemLocation><linkage Sync="TRUE">Server=sde; Service=sde:oracle$sde:oracle11g:mapaspro_oci; User=ordenamientoterritorial; Version=SDE.DEFAULT</linkage><protocol Sync="TRUE">ArcSDE Connection</protocol></itemLocation></itemProps></DataProperties></Esri></metadata>
